cachetto/__init__.py
cachetto/_config.py
cachetto/_core.py
cachetto/_files.py
cachetto/_hashing.py
cachetto/_utils.py
cachetto/py.typed
cachetto-1.2.1.dist-info/METADATA
cachetto-1.2.1.dist-info/WHEEL
cachetto-1.2.1.dist-info/licenses/LICENSE
cachetto-1.2.1.dist-info/RECORD
