Metadata-Version: 2.4
Name: cachetto
Version: 1.2.1
Summary: Disk-based caching for functions returning pickleable objects and pandas DataFrames, plain and simple.
Project-URL: Homepage, https://github.com/plaguss/cachetto/
Project-URL: Source, https://github.com/plaguss/cachetto/
Author-email: agustin <agustin.piqueres@gmail.com>
License-Expression: MIT
License-File: LICENSE
Classifier: Development Status :: 4 - Beta
Classifier: License :: OSI Approved :: MIT License
Classifier: Operating System :: OS Independent
Classifier: Programming Language :: Python
Classifier: Programming Language :: Python :: 3.10
Classifier: Programming Language :: Python :: 3.11
Classifier: Programming Language :: Python :: 3.12
Classifier: Programming Language :: Python :: 3.13
Classifier: Programming Language :: Python :: Implementation :: CPython
Classifier: Programming Language :: Python :: Implementation :: PyPy
Classifier: Topic :: Software Development :: Libraries :: Python Modules
Requires-Python: >=3.10
Requires-Dist: pandas[parquet]>=1.5.3
